svist4get/__init__.py
svist4get/copier.py
svist4get/data_processing.py
svist4get/drawing.py
svist4get/manager.py
svist4get/methods.py
svist4get/svist4get_data/A4_l.cfg
svist4get/svist4get_data/A4_p1.cfg
svist4get/svist4get_data/A4_p2.cfg
svist4get/svist4get_data/MATa.fasta
svist4get/svist4get_data/MATa.fasta.fai
svist4get/svist4get_data/MATa.gtf
svist4get/svist4get_data/RiboCov_cut.bedGraph
svist4get/svist4get_data/RiboProElong_cut.bedGraph
svist4get/svist4get_data/S.cerevisiae.dna.fa
svist4get/svist4get_data/S.cerevisiae.dna.fa.fai
svist4get/svist4get_data/S.cerevisiae.gtf
svist4get/svist4get_data/alt_A4_p1.cfg
svist4get/svist4get_data/alt_palette.txt
svist4get/svist4get_data/mRNACov_cut.bedGraph
svist4get/svist4get_data/mata_ribo1_minus.bedGraph
svist4get/svist4get_data/mata_ribo1_plus.bedGraph
svist4get/svist4get_data/mata_ribo2_minus.bedGraph
svist4get/svist4get_data/mata_ribo2_plus.bedGraph
svist4get/svist4get_data/mata_rna1_minus.bedGraph
svist4get/svist4get_data/mata_rna1_plus.bedGraph
svist4get/svist4get_data/mata_rna2_minus.bedGraph
svist4get/svist4get_data/mata_rna2_plus.bedGraph
svist4get/svist4get_data/palette.txt
svist4get/svist4get_data/triplet_code.txt
svist4get/svist4get_data/fonts/LICENSE
svist4get/svist4get_data/fonts/Lato-Light.ttf
svist4get/svist4get_data/fonts/Lato-Medium.ttf
svist4get/svist4get_data/fonts/Lato-Regular.ttf
svist4get/svist4get_data/fonts/OFL.txt
svist4get/svist4get_data/fonts/iosevka-medium.ttf
svist4get/svist4get_data/fonts/iosevka-regular.ttf
svist4get/svist4get_data/help/help.txt
svist4get/svist4get_data/help/short_help.txt
svist4get-1.3.1.data/scripts/svist4get
svist4get-1.3.1.data/scripts/svist4get_copier
svist4get-1.3.1.dist-info/LICENSE
svist4get-1.3.1.dist-info/METADATA
svist4get-1.3.1.dist-info/WHEEL
svist4get-1.3.1.dist-info/top_level.txt
svist4get-1.3.1.dist-info/RECORD
