Metadata-Version: 2.1
Name: svist4get
Version: 1.3.1
Summary: A simple visualization tool for genomic tracks from sequencing experiments
Home-page: https://github.com/art-egorov/svist4get
Author: Artyom Egorov
Author-email: artyom.egorov@hotmail.com
License: WTFPL
Platform: UNKNOWN
License-File: LICENSE
Requires-Dist: reportlab
Requires-Dist: biopython
Requires-Dist: configs
Requires-Dist: argparse
Requires-Dist: Pybedtools
Requires-Dist: wand
Requires-Dist: statistics
